dreams_core/__init__.py
dreams_core/core.py
dreams_core/dune.py
dreams_core/googlecloud.py
dreams_core-0.2.25.dist-info/LICENSE
dreams_core-0.2.25.dist-info/METADATA
dreams_core-0.2.25.dist-info/WHEEL
dreams_core-0.2.25.dist-info/top_level.txt
dreams_core-0.2.25.dist-info/RECORD
