Metadata-Version: 2.1
Name: dreams_core
Version: 0.2.25
Summary: brought to you by the dreamslabs discord community
Author-email: tentabs <tentabs00@gmail.com>
Project-URL: Community, https://discord.gg/dreamcrypto
Project-URL: Github, https://github.com/dreams-labs/core-functions
Classifier: Programming Language :: Python :: 3.11
Classifier: Development Status :: 3 - Alpha
Classifier: Intended Audience :: Developers
Classifier: License :: OSI Approved :: MIT License
Classifier: Operating System :: OS Independent
Requires-Python: >=3.10
License-File: LICENSE
Requires-Dist: requests>=2.25.1
Requires-Dist: pandas>=1.5.3
Requires-Dist: numpy>=1.19.5
Requires-Dist: aiohttp>=3.8.5
Requires-Dist: google-api-core>=2.19.0
Requires-Dist: google-auth>=2.22.0
Requires-Dist: google-auth-httplib2>=0.1.0
Requires-Dist: google-auth-oauthlib>=1.0.0
Requires-Dist: google-cloud-bigquery>=3.12.0
Requires-Dist: google-cloud-bigquery-storage>=2.25.0
Requires-Dist: google-cloud-storage>=2.10.0
Requires-Dist: google-cloud-secret-manager>=2.3.0
Requires-Dist: pandas-gbq>=0.19.0
Requires-Dist: gspread>=3.4.2
Requires-Dist: fsspec>=2024.6.1
Requires-Dist: gcsfs>=2024.6.1
